[{"nId":"0606502086_X","name":"Thị trấn Chợ Mới (cũ)","slug":"thi-tran-cho-moi-huyen-cho-moi-tinh-bac-kan","propertyCount":8386,"displayOrder":100,"districtId":"06065"},{"nId":"0606502086","name":"Thị trấn Đồng Tâm","slug":"thi-tran-dong-tam-huyen-cho-moi-tinh-bac-kan","propertyCount":8386,"displayOrder":100,"districtId":"06065"},{"nId":"0606502125","name":"Xã Bình Văn","slug":"xa-binh-van-huyen-cho-moi-tinh-bac-kan","propertyCount":8386,"displayOrder":100,"districtId":"06065"},{"nId":"0606502104","name":"Xã Cao Kỳ","slug":"xa-cao-ky-huyen-cho-moi-tinh-bac-kan","propertyCount":8386,"displayOrder":100,"districtId":"06065"},{"nId":"0606502098","name":"Xã Hoà Mục","slug":"xa-hoa-muc-huyen-cho-moi-tinh-bac-kan","propertyCount":8386,"displayOrder":100,"districtId":"06065"},{"nId":"0606502095","name":"Xã Mai Lạp","slug":"xa-mai-lap-huyen-cho-moi-tinh-bac-kan","propertyCount":8386,"displayOrder":100,"districtId":"06065"},{"nId":"0606502122","name":"Xã Như Cố","slug":"xa-nhu-co-huyen-cho-moi-tinh-bac-kan","propertyCount":8386,"displayOrder":100,"districtId":"06065"},{"nId":"0606502107","name":"Xã Nông Hạ","slug":"xa-nong-ha-huyen-cho-moi-tinh-bac-kan","propertyCount":8386,"displayOrder":100,"districtId":"06065"},{"nId":"0606502113_X","name":"Xã Nông Thịnh (cũ)","slug":"xa-nong-thinh-huyen-cho-moi-tinh-bac-kan","propertyCount":8386,"displayOrder":100,"districtId":"06065"},{"nId":"0606502131","name":"Xã Quảng Chu","slug":"xa-quang-chu-huyen-cho-moi-tinh-bac-kan","propertyCount":8386,"displayOrder":100,"districtId":"06065"},{"nId":"0606502089","name":"Xã Tân Sơn","slug":"xa-tan-son-huyen-cho-moi-tinh-bac-kan","propertyCount":8386,"displayOrder":100,"districtId":"06065"},{"nId":"0606502119_X","name":"Xã Thanh Bình (cũ)","slug":"xa-thanh-binh-huyen-cho-moi-tinh-bac-kan","propertyCount":8386,"displayOrder":100,"districtId":"06065"},{"nId":"0606502101","name":"Xã Thanh Mai","slug":"xa-thanh-mai-huyen-cho-moi-tinh-bac-kan","propertyCount":8386,"displayOrder":100,"districtId":"06065"},{"nId":"0606502113","name":"Xã Thanh Thịnh","slug":"xa-thanh-thinh-huyen-cho-moi-tinh-bac-kan","propertyCount":8386,"displayOrder":100,"districtId":"06065"},{"nId":"0606502092","name":"Xã Thanh Vận","slug":"xa-thanh-van-huyen-cho-moi-tinh-bac-kan","propertyCount":8386,"displayOrder":100,"districtId":"06065"},{"nId":"0606502110","name":"Xã Yên Cư","slug":"xa-yen-cu-huyen-cho-moi-tinh-bac-kan","propertyCount":8386,"displayOrder":100,"districtId":"06065"},{"nId":"0606502128_X","name":"Xã Yên Đĩnh (cũ)","slug":"xa-yen-dinh-huyen-cho-moi-tinh-bac-kan","propertyCount":8386,"displayOrder":100,"districtId":"06065"},{"nId":"0606502116","name":"Xã Yên Hân","slug":"xa-yen-han-huyen-cho-moi-tinh-bac-kan","propertyCount":8386,"displayOrder":100,"districtId":"06065"}]