[{"nId":"2725909247","name":"Thị trấn Phố Mới","slug":"thi-tran-pho-moi-huyen-que-vo-tinh-bac-ninh","propertyCount":8433,"displayOrder":100,"districtId":"27259"},{"nId":"2725909262","name":"Xã Bằng An","slug":"xa-bang-an-huyen-que-vo-tinh-bac-ninh","propertyCount":8402,"displayOrder":100,"districtId":"27259"},{"nId":"2725909295","name":"Xã Bồng Lai","slug":"xa-bong-lai-huyen-que-vo-tinh-bac-ninh","propertyCount":8423,"displayOrder":100,"districtId":"27259"},{"nId":"2725909298","name":"Xã Cách Bi","slug":"xa-cach-bi-huyen-que-vo-tinh-bac-ninh","propertyCount":8408,"displayOrder":100,"districtId":"27259"},{"nId":"2725909292","name":"Xã Châu Phong","slug":"xa-chau-phong-que-vo","propertyCount":8386,"displayOrder":100,"districtId":"27259"},{"nId":"2725909313","name":"Xã Chi Lăng","slug":"xa-chi-lang-que-vo","propertyCount":8386,"displayOrder":100,"districtId":"27259"},{"nId":"2725909253","name":"Xã Đại Xuân","slug":"xa-dai-xuan-huyen-que-vo-tinh-bac-ninh","propertyCount":8397,"displayOrder":100,"districtId":"27259"},{"nId":"2725909301","name":"Xã Đào Viên","slug":"xa-dao-vien-que-vo","propertyCount":8386,"displayOrder":100,"districtId":"27259"},{"nId":"2725909310","name":"Xã Đức Long","slug":"xa-duc-long-que-vo","propertyCount":8386,"displayOrder":100,"districtId":"27259"},{"nId":"2725909316","name":"Xã Hán Quảng","slug":"xa-han-quang-huyen-que-vo-tinh-bac-ninh","propertyCount":8387,"displayOrder":100,"districtId":"27259"},{"nId":"2725909307","name":"Xã Mộ Đạo","slug":"xa-mo-dao-que-vo","propertyCount":8386,"displayOrder":100,"districtId":"27259"},{"nId":"2725909289","name":"Xã Ngọc Xá","slug":"xa-ngoc-xa-que-vo","propertyCount":8386,"displayOrder":100,"districtId":"27259"},{"nId":"2725909259","name":"Xã Nhân Hòa","slug":"xa-nhan-hoa-huyen-que-vo-tinh-bac-ninh","propertyCount":8411,"displayOrder":100,"districtId":"27259"},{"nId":"2725909277","name":"Xã Phù Lãng","slug":"xa-phu-lang-que-vo","propertyCount":8386,"displayOrder":100,"districtId":"27259"},{"nId":"2725909274","name":"Xã Phù Lương","slug":"xa-phu-luong-huyen-que-vo-tinh-bac-ninh","propertyCount":8403,"displayOrder":100,"districtId":"27259"},{"nId":"2725909265","name":"Xã Phương Liễu","slug":"xa-phuong-lieu-huyen-que-vo-tinh-bac-ninh","propertyCount":8430,"displayOrder":100,"districtId":"27259"},{"nId":"2725909280","name":"Xã Phượng Mao","slug":"xa-phuong-mao-huyen-que-vo-tinh-bac-ninh","propertyCount":8427,"displayOrder":100,"districtId":"27259"},{"nId":"2725909268","name":"Xã Quế Tân","slug":"xa-que-tan-huyen-que-vo-tinh-bac-ninh","propertyCount":8419,"displayOrder":100,"districtId":"27259"},{"nId":"2725909283","name":"Xã Việt Hùng","slug":"xa-viet-hung-huyen-que-vo-tinh-bac-ninh","propertyCount":8411,"displayOrder":100,"districtId":"27259"},{"nId":"2725909250","name":"Xã Việt Thống","slug":"xa-viet-thong-que-vo","propertyCount":8386,"displayOrder":100,"districtId":"27259"},{"nId":"2725909304","name":"Xã Yên Giả","slug":"xa-yen-gia-que-vo","propertyCount":8386,"displayOrder":100,"districtId":"27259"}]