[{"nId":"3534713294_x","name":"Phường Châu Cầu","slug":"tinh-ha-nam-thanh-pho-phu-ly-phuong-chau-cau","propertyCount":8386,"displayOrder":100,"districtId":"35347"},{"nId":"3534713318","name":"Phường Châu Sơn","slug":"phuong-chau-son-thanh-pho-phu-ly-tinh-ha-nam","propertyCount":8437,"displayOrder":100,"districtId":"35347"},{"nId":"3534713297","name":"Phường Hai Bà Trưng","slug":"phuong-hai-ba-trung-thanh-pho-phu-ly-tinh-ha-nam","propertyCount":8398,"displayOrder":100,"districtId":"35347"},{"nId":"3534713303","name":"Phường Lam Hà","slug":"phuong-lam-ha-phu-ly","propertyCount":8386,"displayOrder":100,"districtId":"35347"},{"nId":"3534713303_x","name":"Phường Lam Hạ","slug":"phuong-lam-ha-phu-ly","propertyCount":8386,"displayOrder":100,"districtId":"35347"},{"nId":"3534713291","name":"Phường Lê Hồng Phong","slug":"phuong-le-hong-phong-thanh-pho-phu-ly-tinh-ha-nam","propertyCount":8429,"displayOrder":100,"districtId":"35347"},{"nId":"3534713309","name":"Phường Liêm Chính","slug":"phuong-liem-chinh-thanh-pho-phu-ly-tinh-ha-nam","propertyCount":8428,"displayOrder":100,"districtId":"35347"},{"nId":"3534713288","name":"Phường Lương Khánh Thiện","slug":"phuong-luong-khanh-thien-thanh-pho-phu-ly-tinh-ha-nam","propertyCount":8393,"displayOrder":100,"districtId":"35347"},{"nId":"3534713294","name":"Phường Minh Khai","slug":"phuong-minh-khai-thanh-pho-phu-ly-tinh-ha-nam","propertyCount":8402,"displayOrder":100,"districtId":"35347"},{"nId":"3534713285","name":"Phường Quang Trung","slug":"phuong-quang-trung-thanh-pho-phu-ly-tinh-ha-nam","propertyCount":8423,"displayOrder":100,"districtId":"35347"},{"nId":"3534713366_x","name":"Phường Tân Hiệp","slug":"tinh-ha-nam-thanh-pho-phu-ly-phuong-tan-hiep","propertyCount":8386,"displayOrder":100,"districtId":"35347"},{"nId":"3534713444_x","name":"Phường Tân Liêm","slug":"tinh-ha-nam-thanh-pho-phu-ly-phuong-tan-liem","propertyCount":8386,"displayOrder":100,"districtId":"35347"},{"nId":"3534713315","name":"Phường Thanh Châu","slug":"phuong-thanh-chau-thanh-pho-phu-ly-tinh-ha-nam","propertyCount":8424,"displayOrder":100,"districtId":"35347"},{"nId":"3534713459","name":"Phường Thanh Tuyền","slug":"phuong-thanh-tuyen-thanh-pho-phu-ly-tinh-ha-nam","propertyCount":8417,"displayOrder":100,"districtId":"35347"},{"nId":"3534713300","name":"Phường Trần Hưng Đạo","slug":"phuong-tran-hung-dao-thanh-pho-phu-ly-tinh-ha-nam","propertyCount":8401,"displayOrder":100,"districtId":"35347"},{"nId":"3534713507","name":"Xã Đinh Xá","slug":"xa-dinh-xa-thanh-pho-phu-ly-tinh-ha-nam","propertyCount":8388,"displayOrder":100,"districtId":"35347"},{"nId":"3534713426","name":"Xã Kim Bình","slug":"xa-kim-binh-thanh-pho-phu-ly-tinh-ha-nam","propertyCount":8404,"displayOrder":100,"districtId":"35347"},{"nId":"3534713312","name":"Xã Liêm Chung","slug":"xa-liem-chung-thanh-pho-phu-ly-tinh-ha-nam","propertyCount":8415,"displayOrder":100,"districtId":"35347"},{"nId":"3534713447","name":"Xã Liêm Tiết","slug":"xa-liem-tiet-thanh-pho-phu-ly-tinh-ha-nam","propertyCount":8413,"displayOrder":100,"districtId":"35347"},{"nId":"3534713444","name":"Xã Liêm Tuyền","slug":"xa-liem-tuyen-thanh-pho-phu-ly-tinh-ha-nam","propertyCount":8424,"displayOrder":100,"districtId":"35347"},{"nId":"3534713306","name":"Xã Phù Vân","slug":"xa-phu-van-thanh-pho-phu-ly-tinh-ha-nam","propertyCount":8423,"displayOrder":100,"districtId":"35347"},{"nId":"3534713381","name":"Xã Tiên Hải","slug":"xa-tien-hai-thanh-pho-phu-ly-tinh-ha-nam","propertyCount":8394,"displayOrder":100,"districtId":"35347"},{"nId":"3534713372","name":"Xã Tiên Hiệp","slug":"xa-tien-hiep-thanh-pho-phu-ly-tinh-ha-nam","propertyCount":8407,"displayOrder":100,"districtId":"35347"},{"nId":"3534713366","name":"Xã Tiên Tân","slug":"xa-tien-tan-thanh-pho-phu-ly-tinh-ha-nam","propertyCount":8409,"displayOrder":100,"districtId":"35347"},{"nId":"3534713513","name":"Xã Trịnh Xá","slug":"xa-trinh-xa-thanh-pho-phu-ly-tinh-ha-nam","propertyCount":8404,"displayOrder":100,"districtId":"35347"}]