[{"nId":"4445719249","name":"Thị trấn Kiến Giang","slug":"thi-tran-kien-giang-huyen-le-thuy-tinh-quang-binh","propertyCount":8394,"displayOrder":100,"districtId":"44457"},{"nId":"4445719246","name":"Thị trấn NT Lệ Ninh","slug":"thi-tran-nt-le-ninh-huyen-le-thuy-tinh-quang-binh","propertyCount":8387,"displayOrder":100,"districtId":"44457"},{"nId":"4445719264","name":"Xã An Thủy","slug":"xa-an-thuy-huyen-le-thuy-tinh-quang-binh","propertyCount":8392,"displayOrder":100,"districtId":"44457"},{"nId":"4445719270","name":"Xã Cam Thủy","slug":"xa-cam-thuy-huyen-le-thuy-tinh-quang-binh","propertyCount":8392,"displayOrder":100,"districtId":"44457"},{"nId":"4445719291","name":"Xã Dương Thủy","slug":"xa-duong-thuy-huyen-le-thuy-tinh-quang-binh","propertyCount":8392,"displayOrder":100,"districtId":"44457"},{"nId":"4445719258","name":"Xã Hoa Thủy","slug":"xa-hoa-thuy-huyen-le-thuy-tinh-quang-binh","propertyCount":8386,"displayOrder":100,"districtId":"44457"},{"nId":"4445719252","name":"Xã Hồng Thủy","slug":"xa-hong-thuy-huyen-le-thuy-tinh-quang-binh","propertyCount":8396,"displayOrder":100,"districtId":"44457"},{"nId":"4445719288","name":"Xã Hưng Thủy","slug":"xa-hung-thuy-huyen-le-thuy-tinh-quang-binh","propertyCount":8389,"displayOrder":100,"districtId":"44457"},{"nId":"4445719318","name":"Xã Kim Thủy","slug":"xa-kim-thuy-huyen-le-thuy-tinh-quang-binh","propertyCount":8386,"displayOrder":100,"districtId":"44457"},{"nId":"4445719327","name":"Xã Lâm Thủy","slug":"xa-lam-thuy-huyen-le-thuy-tinh-quang-binh","propertyCount":8386,"displayOrder":100,"districtId":"44457"},{"nId":"4445719285","name":"Xã Liên Thủy","slug":"xa-lien-thuy-huyen-le-thuy-tinh-quang-binh","propertyCount":8395,"displayOrder":100,"districtId":"44457"},{"nId":"4445719279","name":"Xã Lộc Thủy","slug":"xa-loc-thuy-huyen-le-thuy-tinh-quang-binh","propertyCount":8390,"displayOrder":100,"districtId":"44457"},{"nId":"4445719309","name":"Xã Mai Thủy","slug":"xa-mai-thuy-huyen-le-thuy-tinh-quang-binh","propertyCount":8394,"displayOrder":100,"districtId":"44457"},{"nId":"4445719303","name":"Xã Mỹ Thủy","slug":"xa-my-thuy-huyen-le-thuy-tinh-quang-binh","propertyCount":8391,"displayOrder":100,"districtId":"44457"},{"nId":"4445719273","name":"Xã Ngân Thủy","slug":"xa-ngan-thuy-huyen-le-thuy-tinh-quang-binh","propertyCount":8386,"displayOrder":100,"districtId":"44457"},{"nId":"4445719306","name":"Xã Ngư Thủy","slug":"xa-ngu-thuy-le-thuy","propertyCount":8386,"displayOrder":100,"districtId":"44457"},{"nId":"4445719306_x","name":"Xã Ngư Thủy ","slug":"xa-ngu-thuy-le-thuy","propertyCount":8386,"displayOrder":100,"districtId":"44457"},{"nId":"4445719255","name":"Xã Ngư Thủy Bắc","slug":"xa-ngu-thuy-bac-huyen-le-thuy-tinh-quang-binh","propertyCount":8396,"displayOrder":100,"districtId":"44457"},{"nId":"4445719306_X","name":"Xã Ngư Thủy Nam (cũ)","slug":"xa-ngu-thuy-nam-huyen-le-thuy-tinh-quang-binh","propertyCount":8386,"displayOrder":100,"districtId":"44457"},{"nId":"4445719282_X","name":"Xã Ngư Thủy Trung (cũ)","slug":"xa-ngu-thuy-trung-huyen-le-thuy-tinh-quang-binh","propertyCount":8386,"displayOrder":100,"districtId":"44457"},{"nId":"4445719267","name":"Xã Phong Thủy","slug":"xa-phong-thuy-huyen-le-thuy-tinh-quang-binh","propertyCount":8390,"displayOrder":100,"districtId":"44457"},{"nId":"4445719297","name":"Xã Phú Thủy","slug":"xa-phu-thuy-huyen-le-thuy-tinh-quang-binh","propertyCount":8388,"displayOrder":100,"districtId":"44457"},{"nId":"4445719312","name":"Xã Sen Thủy","slug":"xa-sen-thuy-huyen-le-thuy-tinh-quang-binh","propertyCount":8392,"displayOrder":100,"districtId":"44457"},{"nId":"4445719276","name":"Xã Sơn Thủy","slug":"xa-son-thuy-huyen-le-thuy-tinh-quang-binh","propertyCount":8388,"displayOrder":100,"districtId":"44457"},{"nId":"4445719294","name":"Xã Tân Thủy","slug":"xa-tan-thuy-huyen-le-thuy-tinh-quang-binh","propertyCount":8389,"displayOrder":100,"districtId":"44457"},{"nId":"4445719315","name":"Xã Thái Thủy","slug":"xa-thai-thuy-huyen-le-thuy-tinh-quang-binh","propertyCount":8391,"displayOrder":100,"districtId":"44457"},{"nId":"4445719261","name":"Xã Thanh Thủy","slug":"xa-thanh-thuy-huyen-le-thuy-tinh-quang-binh","propertyCount":8396,"displayOrder":100,"districtId":"44457"},{"nId":"4445719321","name":"Xã Trường Thủy","slug":"xa-truong-thuy-huyen-le-thuy-tinh-quang-binh","propertyCount":8394,"displayOrder":100,"districtId":"44457"},{"nId":"4445719324_X","name":"Xã Văn Thủy (cũ)","slug":"xa-van-thuy-huyen-le-thuy-tinh-quang-binh","propertyCount":8386,"displayOrder":100,"districtId":"44457"},{"nId":"4445719300","name":"Xã Xuân Thủy","slug":"xa-xuan-thuy-huyen-le-thuy-tinh-quang-binh","propertyCount":8388,"displayOrder":100,"districtId":"44457"}]