[{"nId":"5255121994","name":"Thị trấn Vân Canh","slug":"thi-tran-van-canh-huyen-van-canh-tinh-binh-dinh","propertyCount":8395,"displayOrder":100,"districtId":"52551"},{"nId":"5255122006","name":"Xã Canh Hiển","slug":"xa-canh-hien-huyen-van-canh-tinh-binh-dinh","propertyCount":8394,"displayOrder":100,"districtId":"52551"},{"nId":"5255122000","name":"Xã Canh Hiệp","slug":"xa-canh-hiep-huyen-van-canh-tinh-binh-dinh","propertyCount":8395,"displayOrder":100,"districtId":"52551"},{"nId":"5255122012","name":"Xã Canh Hòa","slug":"xa-canh-hoa-huyen-van-canh-tinh-binh-dinh","propertyCount":8392,"displayOrder":100,"districtId":"52551"},{"nId":"5255121997","name":"Xã Canh Liên","slug":"xa-canh-lien-huyen-van-canh-tinh-binh-dinh","propertyCount":8386,"displayOrder":100,"districtId":"52551"},{"nId":"5255122009","name":"Xã Canh Thuận","slug":"xa-canh-thuan-huyen-van-canh-tinh-binh-dinh","propertyCount":8386,"displayOrder":100,"districtId":"52551"},{"nId":"5255122003","name":"Xã Canh Vinh","slug":"xa-canh-vinh-huyen-van-canh-tinh-binh-dinh","propertyCount":8403,"displayOrder":100,"districtId":"52551"}]