[{"nId":"8079427694","name":"Phường 1","slug":"phuong-1-thanh-pho-tan-an-tinh-long-an","propertyCount":8408,"displayOrder":100,"districtId":"80794"},{"nId":"8079427688","name":"Phường 2","slug":"phuong-2-thanh-pho-tan-an-tinh-long-an","propertyCount":8416,"displayOrder":100,"districtId":"80794"},{"nId":"8079427697","name":"Phường 3","slug":"phuong-3-thanh-pho-tan-an-tinh-long-an","propertyCount":8442,"displayOrder":100,"districtId":"80794"},{"nId":"8079427691","name":"Phường 4","slug":"phuong-4-thanh-pho-tan-an-tinh-long-an","propertyCount":8435,"displayOrder":100,"districtId":"80794"},{"nId":"8079427685","name":"Phường 5","slug":"phuong-5-thanh-pho-tan-an-tinh-long-an","propertyCount":8436,"displayOrder":100,"districtId":"80794"},{"nId":"8079427700","name":"Phường 6","slug":"phuong-6-thanh-pho-tan-an-tinh-long-an","propertyCount":8439,"displayOrder":100,"districtId":"80794"},{"nId":"8079427698","name":"Phường 7","slug":"phuong-7-thanh-pho-tan-an-tinh-long-an","propertyCount":8421,"displayOrder":100,"districtId":"80794"},{"nId":"8079427715","name":"Phường Khánh Hậu","slug":"phuong-khanh-hau-thanh-pho-tan-an-tinh-long-an","propertyCount":8434,"displayOrder":100,"districtId":"80794"},{"nId":"8079427692","name":"Phường Tân Khánh","slug":"phuong-tan-khanh-thanh-pho-tan-an-tinh-long-an","propertyCount":8420,"displayOrder":100,"districtId":"80794"},{"nId":"8079427718","name":"Xã An Vĩnh Ngãi","slug":"xa-an-vinh-ngai-thanh-pho-tan-an-tinh-long-an","propertyCount":8426,"displayOrder":100,"districtId":"80794"},{"nId":"8079427712","name":"Xã Bình Tâm","slug":"xa-binh-tam-thanh-pho-tan-an-tinh-long-an","propertyCount":8433,"displayOrder":100,"districtId":"80794"},{"nId":"8079427703","name":"Xã Hướng Thọ Phú","slug":"xa-huong-tho-phu-thanh-pho-tan-an-tinh-long-an","propertyCount":8423,"displayOrder":100,"districtId":"80794"},{"nId":"8079427709","name":"Xã Lợi Bình Nhơn","slug":"xa-loi-binh-nhon-thanh-pho-tan-an-tinh-long-an","propertyCount":8427,"displayOrder":100,"districtId":"80794"},{"nId":"8079427706","name":"Xã Nhơn Thạnh Trung","slug":"xa-nhon-thanh-trung-thanh-pho-tan-an-tinh-long-an","propertyCount":8420,"displayOrder":100,"districtId":"80794"}]