[{"nId":"9393331381","name":"Thị trấn Mái Dầm","slug":"thi-tran-mai-dam-huyen-chau-thanh-tinh-hau-giang","propertyCount":8398,"displayOrder":100,"districtId":"93933"},{"nId":"9393331366","name":"Thị Trấn Ngã Sáu","slug":"thi-tran-nga-sau-huyen-chau-thanh-tinh-hau-giang","propertyCount":8390,"displayOrder":100,"districtId":"93933"},{"nId":"9393331375","name":"Xã Đông Phú","slug":"xa-dong-phu-huyen-chau-thanh-tinh-hau-giang","propertyCount":8396,"displayOrder":100,"districtId":"93933"},{"nId":"9393331384","name":"Xã Đông Phước","slug":"xa-dong-phuoc-huyen-chau-thanh-tinh-hau-giang","propertyCount":8389,"displayOrder":100,"districtId":"93933"},{"nId":"9393331387","name":"Xã Đông Phước A","slug":"xa-dong-phuoc-a-huyen-chau-thanh-tinh-hau-giang","propertyCount":8390,"displayOrder":100,"districtId":"93933"},{"nId":"9393331369","name":"Xã Đông Thạnh","slug":"xa-dong-thanh-huyen-chau-thanh-tinh-hau-giang","propertyCount":8390,"displayOrder":100,"districtId":"93933"},{"nId":"9393331372_X","name":"Xã Phú An (cũ)","slug":"xa-phu-an-huyen-chau-thanh-tinh-hau-giang","propertyCount":8386,"displayOrder":100,"districtId":"93933"},{"nId":"9393331378","name":"Xã Phú Hữu","slug":"xa-phu-huu-chau-thanh","propertyCount":8386,"displayOrder":100,"districtId":"93933"},{"nId":"9393331379","name":"Xã Phú Tân","slug":"xa-phu-tan-chau-thanh","propertyCount":8386,"displayOrder":100,"districtId":"93933"}]