[{"nId":"9393131343_X","name":"Phường Hiệp Thành","slug":"phuong-hiep-thanh-thi-xa-nga-bay-tinh-hau-giang","propertyCount":8386,"displayOrder":100,"districtId":"93931_X"},{"nId":"9393131341_X","name":"Phường Lái Hiếu","slug":"phuong-lai-hieu-thi-xa-nga-bay-tinh-hau-giang","propertyCount":8386,"displayOrder":100,"districtId":"93931_X"},{"nId":"9393131340_X","name":"Phường Ngã Bảy","slug":"phuong-nga-bay-thi-xa-nga-bay-tinh-hau-giang","propertyCount":8386,"displayOrder":100,"districtId":"93931_X"},{"nId":"9393131411_X","name":"Xã Đại Thành","slug":"xa-dai-thanh-thi-xa-nga-bay-tinh-hau-giang","propertyCount":8386,"displayOrder":100,"districtId":"93931_X"},{"nId":"9393131344_X","name":"Xã Hiệp Lợi","slug":"xa-hiep-loi-thi-xa-nga-bay-tinh-hau-giang","propertyCount":8386,"displayOrder":100,"districtId":"93931_X"},{"nId":"9393131414_X","name":"Xã Tân Thành","slug":"xa-tan-thanh-thi-xa-nga-bay-tinh-hau-giang","propertyCount":8386,"displayOrder":100,"districtId":"93931_X"}]