[{"nId":"9494731684","name":"Thị trấn Mỹ Xuyên","slug":"thi-tran-my-xuyen-huyen-my-xuyen-tinh-soc-trang","propertyCount":8408,"displayOrder":100,"districtId":"94947"},{"nId":"9494731690","name":"Xã Đại Tâm","slug":"xa-dai-tam-huyen-my-xuyen-tinh-soc-trang","propertyCount":8437,"displayOrder":100,"districtId":"94947"},{"nId":"9494731720","name":"Xã Gia Hòa 1","slug":"xa-gia-hoa-1-huyen-my-xuyen-tinh-soc-trang","propertyCount":8397,"displayOrder":100,"districtId":"94947"},{"nId":"9494731726","name":"Xã Gia Hòa 2","slug":"xa-gia-hoa-2-huyen-my-xuyen-tinh-soc-trang","propertyCount":8398,"displayOrder":100,"districtId":"94947"},{"nId":"9494731717","name":"Xã Hòa Tú 1","slug":"xa-hoa-tu-1-huyen-my-xuyen-tinh-soc-trang","propertyCount":8409,"displayOrder":100,"districtId":"94947"},{"nId":"9494731729_X","name":"Xã Hòa Tú 2 (cũ)","slug":"xa-hoa-tu-2-huyen-my-xuyen-tinh-soc-trang","propertyCount":8386,"displayOrder":100,"districtId":"94947"},{"nId":"9494731729","name":"Xã Hòa Tú II","slug":"xa-hoa-tu-ii-huyen-my-xuyen-tinh-soc-trang","propertyCount":8386,"displayOrder":100,"districtId":"94947"},{"nId":"9494731711","name":"Xã Ngọc Đông","slug":"xa-ngoc-dong-huyen-my-xuyen-tinh-soc-trang","propertyCount":8397,"displayOrder":100,"districtId":"94947"},{"nId":"9494731723","name":"Xã Ngọc Tố","slug":"xa-ngoc-to-huyen-my-xuyen-tinh-soc-trang","propertyCount":8404,"displayOrder":100,"districtId":"94947"},{"nId":"9494731693","name":"Xã Tham Đôn","slug":"xa-tham-don-huyen-my-xuyen-tinh-soc-trang","propertyCount":8410,"displayOrder":100,"districtId":"94947"},{"nId":"9494731708","name":"Xã Thạnh Phú","slug":"xa-thanh-phu-huyen-my-xuyen-tinh-soc-trang","propertyCount":8410,"displayOrder":100,"districtId":"94947"},{"nId":"9494731714","name":"Xã Thạnh Quới","slug":"xa-thanh-quoi-huyen-my-xuyen-tinh-soc-trang","propertyCount":8408,"displayOrder":100,"districtId":"94947"}]