[{"nId":"06061","name":"Huyện Ba Bể","slug":"huyen-ba-be-tinh-bac-kan","propertyCount":8386,"displayOrder":100,"provinceId":"06"},{"nId":"06063","name":"Huyện Bạch Thông","slug":"huyen-bach-thong-tinh-bac-kan","propertyCount":8386,"displayOrder":100,"provinceId":"06"},{"nId":"06064","name":"Huyện Chợ Đồn","slug":"huyen-cho-don-tinh-bac-kan","propertyCount":8386,"displayOrder":100,"provinceId":"06"},{"nId":"06065","name":"Huyện Chợ Mới","slug":"huyen-cho-moi-tinh-bac-kan","propertyCount":8386,"displayOrder":100,"provinceId":"06"},{"nId":"06066","name":"Huyện Na Rì","slug":"huyen-na-ri-tinh-bac-kan","propertyCount":8386,"displayOrder":100,"provinceId":"06"},{"nId":"06062","name":"Huyện Ngân Sơn","slug":"huyen-ngan-son-tinh-bac-kan","propertyCount":8386,"displayOrder":100,"provinceId":"06"},{"nId":"06060","name":"Huyện Pác Nặm","slug":"huyen-pac-nam-tinh-bac-kan","propertyCount":8386,"displayOrder":100,"provinceId":"06"},{"nId":"06058","name":"Thành Phố Bắc Kạn","slug":"thanh-pho-bac-kan-tinh-bac-kan","propertyCount":8386,"displayOrder":100,"provinceId":"06"}]